rlr/__init__.py
rlr/backport.py
rlr/crossvalidation.py
rlr/lr.py
rlr-2.4.6.dist-info/COPYING
rlr-2.4.6.dist-info/METADATA
rlr-2.4.6.dist-info/WHEEL
rlr-2.4.6.dist-info/top_level.txt
rlr-2.4.6.dist-info/RECORD
